map3C/__init__.py
map3C/__main__.py
map3C/_version.py
map3C/demultiplex/__init__.py
map3C/demultiplex/demultiplex.py
map3C/demultiplex/snakemake/GAGE-seq/demultiplex_BC1.smk
map3C/demultiplex/snakemake/GAGE-seq/demultiplex_BC2.smk
map3C/demultiplex/snakemake/snm3Cseq/demultiplex.smk
map3C/mapping/__init__.py
map3C/mapping/allc.py
map3C/mapping/call_contacts.py
map3C/mapping/compute_restriction_sites.py
map3C/mapping/contam_filter.py
map3C/mapping/cut_analysis.py
map3C/mapping/mapping.py
map3C/mapping/mask.py
map3C/mapping/pairs_generator.py
map3C/mapping/pairtools.py
map3C/mapping/phase.py
map3C/mapping/utils.py
map3C/mapping/snakemake/m3C/mapping.smk
map3C/mapping/snakemake/m3C/rules/align.smk
map3C/mapping/snakemake/m3C/rules/align_bisulfite.smk
map3C/mapping/snakemake/m3C/rules/align_dna.smk
map3C/mapping/snakemake/m3C/rules/allc.smk
map3C/mapping/snakemake/m3C/rules/contacts.smk
map3C/mapping/snakemake/m3C/rules/coord_sort_bam.smk
map3C/mapping/snakemake/m3C/rules/dedup_contacts.smk
map3C/mapping/snakemake/m3C/rules/lowcov_contacts.smk
map3C/mapping/snakemake/m3C/rules/mask.smk
map3C/mapping/snakemake/m3C/rules/merge_sort.smk
map3C/mapping/snakemake/m3C/rules/mkdup.smk
map3C/mapping/snakemake/m3C/rules/mkdup_bisulfite.smk
map3C/mapping/snakemake/m3C/rules/preprocess.smk
map3C/mapping/snakemake/m3C/rules/read_analysis.smk
map3C/mapping/snakemake/m3C/rules/reformat.smk
map3C/mapping/snakemake/m3C/rules/sort_contacts.smk
map3C/mapping/snakemake/m3C/rules/stats.smk
map3C/mapping/snakemake/m3C/rules/trim/trim_cutadapt_pe.smk
map3C/mapping/snakemake/m3C/rules/trim/trim_hires.smk
map3C/mapping/snakemake/m3C/rules/trim/trim_meta.smk
map3C/mapping/snakemake/mCT/mapping.smk
map3C/mapping/snakemake/mCT/rules/align.smk
map3C/mapping/snakemake/mCT/rules/align_biscuit.smk
map3C/mapping/snakemake/mCT/rules/align_star.smk
map3C/mapping/snakemake/mCT/rules/postprocess.smk
map3C/mapping/snakemake/mCT/rules/postprocess_dna.smk
map3C/mapping/snakemake/mCT/rules/postprocess_rna.smk
map3c-0.0.7.dist-info/licenses/LICENSE
map3c-0.0.7.dist-info/METADATA
map3c-0.0.7.dist-info/WHEEL
map3c-0.0.7.dist-info/entry_points.txt
map3c-0.0.7.dist-info/top_level.txt
map3c-0.0.7.dist-info/RECORD
