Metadata-Version: 2.4
Name: map3C
Version: 0.0.7
Summary: A package for mapping 3C/Hi-C data
Home-page: https://github.com/solveforj/map3C
Author: Joseph Galasso
Author-email: jgalasso1@g.ucla.edu
License: MIT
License-File: LICENSE
Dynamic: author
Dynamic: author-email
Dynamic: description
Dynamic: description-content-type
Dynamic: home-page
Dynamic: license
Dynamic: license-file
Dynamic: summary
